DDS_All/DDS_All.pyi
DDS_All/__init__.py
DDS_All/py.typed
DDS_All/bin/cp310-win_amd64/DDS_All.pyd
DDS_All/bin/cp311-win_amd64/DDS_All.pyd
DDS_All/bin/cp312-win_amd64/DDS_All.pyd
DDS_All/bin/cp313-win_amd64/DDS_All.pyd
DDS_All/bin/cp39-win_amd64/DDS_All.pyd
DDS_All/libs/ZRDDSC_VS2019.dll
DDS_All/libs/ZRDDSC_VS2019.lib
DDS_All/libs/ZRDDSCd_VS2019.dll
DDS_All/libs/ZRDDSCd_VS2019.lib
DDS_All/libs/ZRDDSCd_VS2019.pdb
DDS_All/libs/ZRDDSCpp_VS2019.dll
DDS_All/libs/ZRDDSCpp_VS2019.lib
DDS_All/libs/ZRDDSCppd_VS2019.dll
DDS_All/libs/ZRDDSCppd_VS2019.lib
DDS_All/libs/ZRDDSCppd_VS2019.pdb
DDS_All/libs/ZRDDSCppz_VS2019.lib
DDS_All/libs/ZRDDSCppzd_VS2019.lib
DDS_All/libs/ZRDDSCppzd_VS2019.pdb
DDS_All/libs/ZRDDSCz_VS2019.lib
DDS_All/libs/ZRDDSCzd_VS2019.lib
DDS_All/libs/ZRDDSCzd_VS2019.pdb
dds_all-0.3.7.dist-info/METADATA
dds_all-0.3.7.dist-info/WHEEL
dds_all-0.3.7.dist-info/top_level.txt
dds_all-0.3.7.dist-info/RECORD
